README.md
my_unique_test/__init__.py
my_unique_test/_version.py
my_unique_test-0.9.9.dist-info/LICENSE
my_unique_test-0.9.9.dist-info/WHEEL
my_unique_test-0.9.9.dist-info/METADATA
my_unique_test-0.9.9.dist-info/RECORD
